flake8_tidy_imports/__init__.py
flake8_tidy_imports/py.typed
flake8_tidy_imports-4.12.0.dist-info/licenses/LICENSE
flake8_tidy_imports-4.12.0.dist-info/METADATA
flake8_tidy_imports-4.12.0.dist-info/WHEEL
flake8_tidy_imports-4.12.0.dist-info/entry_points.txt
flake8_tidy_imports-4.12.0.dist-info/top_level.txt
flake8_tidy_imports-4.12.0.dist-info/RECORD
